hacker_dictionary/__init__.py
hacker_dictionary/hacker_dictionary.py
hacker_dictionary-0.0.1.dist-info/LICENSE
hacker_dictionary-0.0.1.dist-info/METADATA
hacker_dictionary-0.0.1.dist-info/WHEEL
hacker_dictionary-0.0.1.dist-info/top_level.txt
hacker_dictionary-0.0.1.dist-info/RECORD
