Metadata-Version: 2.1
Name: hacker-dictionary
Version: 0.0.1
Summary: string to date
Author: YGXB
Author-email: 839682307@qq.com
License: MIT
Platform: UNKNOWN
License-File: LICENSE
